sqlalchemy/__init__.py
sqlalchemy/cimmutabledict.so
sqlalchemy/cprocessors.so
sqlalchemy/cresultproxy.so
sqlalchemy/cutils.so
sqlalchemy/events.py
sqlalchemy/exc.py
sqlalchemy/inspection.py
sqlalchemy/log.py
sqlalchemy/processors.py
sqlalchemy/schema.py
sqlalchemy/types.py
sqlalchemy/connectors/__init__.py
sqlalchemy/connectors/mxodbc.py
sqlalchemy/connectors/pyodbc.py
sqlalchemy/databases/__init__.py
sqlalchemy/dialects/__init__.py
sqlalchemy/dialects/firebird/__init__.py
sqlalchemy/dialects/firebird/base.py
sqlalchemy/dialects/firebird/fdb.py
sqlalchemy/dialects/firebird/kinterbasdb.py
sqlalchemy/dialects/mssql/__init__.py
sqlalchemy/dialects/mssql/base.py
sqlalchemy/dialects/mssql/information_schema.py
sqlalchemy/dialects/mssql/mxodbc.py
sqlalchemy/dialects/mssql/provision.py
sqlalchemy/dialects/mssql/pymssql.py
sqlalchemy/dialects/mssql/pyodbc.py
sqlalchemy/dialects/mysql/__init__.py
sqlalchemy/dialects/mysql/base.py
sqlalchemy/dialects/mysql/cymysql.py
sqlalchemy/dialects/mysql/dml.py
sqlalchemy/dialects/mysql/enumerated.py
sqlalchemy/dialects/mysql/json.py
sqlalchemy/dialects/mysql/mysqlconnector.py
sqlalchemy/dialects/mysql/mysqldb.py
sqlalchemy/dialects/mysql/oursql.py
sqlalchemy/dialects/mysql/provision.py
sqlalchemy/dialects/mysql/pymysql.py
sqlalchemy/dialects/mysql/pyodbc.py
sqlalchemy/dialects/mysql/reflection.py
sqlalchemy/dialects/mysql/types.py
sqlalchemy/dialects/oracle/__init__.py
sqlalchemy/dialects/oracle/base.py
sqlalchemy/dialects/oracle/cx_oracle.py
sqlalchemy/dialects/oracle/provision.py
sqlalchemy/dialects/postgresql/__init__.py
sqlalchemy/dialects/postgresql/array.py
sqlalchemy/dialects/postgresql/base.py
sqlalchemy/dialects/postgresql/dml.py
sqlalchemy/dialects/postgresql/ext.py
sqlalchemy/dialects/postgresql/hstore.py
sqlalchemy/dialects/postgresql/json.py
sqlalchemy/dialects/postgresql/pg8000.py
sqlalchemy/dialects/postgresql/provision.py
sqlalchemy/dialects/postgresql/psycopg2.py
sqlalchemy/dialects/postgresql/psycopg2cffi.py
SQLAlchemy_mmeyer724-1.4.0b1.dist-info/LICENSE
SQLAlchemy_mmeyer724-1.4.0b1.dist-info/METADATA
SQLAlchemy_mmeyer724-1.4.0b1.dist-info/WHEEL
SQLAlchemy_mmeyer724-1.4.0b1.dist-info/top_level.txt
SQLAlchemy_mmeyer724-1.4.0b1.dist-info/RECORD
