Metadata-Version: 2.1
Name: SQLAlchemy-mmeyer724
Version: 1.4.0b1
Summary: Database Abstraction Library
Home-page: http://www.sqlalchemy.org
Author: Mike Bayer
Author-email: mike_mp@zzzcomputing.com
License: MIT
Project-URL: Issue Tracker, https://github.com/sqlalchemy/sqlalchemy/
Project-URL: Documentation, https://docs.sqlalchemy.org
Platform: UNKNOWN
Classifier: Development Status :: 5 - Production/Stable
Classifier: Intended Audience :: Developers
Classifier: License :: OSI Approved :: MIT License
Classifier: Operating System :: OS Independent
Classifier: Programming Language :: Python
Classifier: Programming Language :: Python :: 2
Classifier: Programming Language :: Python :: 2.7
Classifier: Programming Language :: Python :: 3
Classifier: Programming Language :: Python :: 3.5
Classifier: Programming Language :: Python :: 3.6
Classifier: Programming Language :: Python :: 3.7
Classifier: Programming Language :: Python :: 3.8
Classifier: Programming Language :: Python :: Implementation :: CPython
Classifier: Programming Language :: Python :: Implementation :: PyPy
Classifier: Topic :: Database :: Front-Ends
Requires-Python: >=2.7, !=3.0.*, !=3.1.*, !=3.2.*, !=3.3.*, !=3.4.*
Provides-Extra: mssql
Requires-Dist: pyodbc ; extra == 'mssql'
Provides-Extra: mssql_pymssql
Requires-Dist: pymssql ; extra == 'mssql_pymssql'
Provides-Extra: mssql_pyodbc
Requires-Dist: pyodbc ; extra == 'mssql_pyodbc'
Provides-Extra: mysql
Requires-Dist: mysqlclient (<2,>=1.4.0) ; (python_version < "3") and extra == 'mysql'
Requires-Dist: mysqlclient (>=1.4.0) ; (python_version >= "3") and extra == 'mysql'
Provides-Extra: oracle
Requires-Dist: cx-oracle (<8,>=7) ; (python_version < "3") and extra == 'oracle'
Requires-Dist: cx-oracle (>=7) ; (python_version >= "3") and extra == 'oracle'
Provides-Extra: postgresql
Requires-Dist: psycopg2 (>=2.7) ; extra == 'postgresql'
Provides-Extra: postgresql_pg8000
Requires-Dist: pg8000 ; extra == 'postgresql_pg8000'
Provides-Extra: postgresql_psycopg2binary
Requires-Dist: psycopg2-binary ; extra == 'postgresql_psycopg2binary'
Provides-Extra: postgresql_psycopg2cffi
Requires-Dist: psycopg2cffi ; extra == 'postgresql_psycopg2cffi'
Provides-Extra: pymysql
Requires-Dist: pymysql ; extra == 'pymysql'
